Metadata-Version: 2.1
Name: discord-port
Version: 1.4
Summary: discord_port is a simple way to make auth with the Discord API!
Home-page: UNKNOWN
Author: airbu
Author-email: airbu.email@gmail.com
License: MIT
Keywords: discord,api,oauth
Platform: UNKNOWN
Classifier: Development Status :: 1 - Planning
Classifier: Intended Audience :: Developers
Classifier: Programming Language :: Python :: 3
Classifier: Operating System :: Unix
Classifier: Operating System :: MacOS :: MacOS X
Classifier: Operating System :: Microsoft :: Windows
